[{"u":"2026-07-20","o":"BOS","d":"ATL","g":-1,"sig":"LEARNING","cash":434,"gc":0,"fc":4,"dep":"2026-07-21"},{"u":"2026-07-20","o":"BOS","d":"ATL","g":-1,"sig":"LEARNING","cash":338,"gc":0,"fc":6,"dep":"2026-07-22"},{"u":"2026-07-20","o":"BOS","d":"ATL","g":-1,"sig":"LEARNING","cash":290,"gc":0,"fc":5,"dep":"2026-07-23"},{"u":"2026-07-20","o":"BOS","d":"ATL","g":157.97,"sig":"LEARNING","cash":290,"gc":2,"fc":7,"dep":"2026-07-24"},{"u":"2026-07-20","o":"BOS","d":"ATL","g":-1,"sig":"LEARNING","cash":241,"gc":0,"fc":7,"dep":"2026-07-25"}]